ruamel/yaml/base/__init__.py
ruamel.yaml.base-0.3.2.dist-info/METADATA
ruamel.yaml.base-0.3.2.dist-info/WHEEL
ruamel.yaml.base-0.3.2.dist-info/entry_points.txt
ruamel.yaml.base-0.3.2.dist-info/namespace_packages.txt
ruamel.yaml.base-0.3.2.dist-info/top_level.txt
ruamel.yaml.base-0.3.2.dist-info/RECORD
