Metadata-Version: 2.1
Name: ruamel.yaml.base
Version: 0.3.2
Summary: YAMLBase class with saving loading and version support
Home-page: https://sourceforge.net/p/ruamel-yaml-base/code/ci/default/tree
Author: Anthon van der Neut
Author-email: a.van.der.neut@ruamel.eu
License: Copyright Ruamel bvba 2007-2021
Classifier: Development Status :: 4 - Beta
Classifier: Intended Audience :: Developers
Classifier: License :: Other/Proprietary License
Classifier: Operating System :: OS Independent
Classifier: Programming Language :: Python
Requires-Python: >=3
